pygcransac-0.1.1.dist-info/WHEEL
pygcransac-0.1.1.dist-info/LICENSE
pygcransac-0.1.1.dist-info/RECORD
pygcransac-0.1.1.dist-info/top_level.txt
pygcransac-0.1.1.dist-info/METADATA
pygcransac/pygcransac.cpython-312-x86_64-linux-gnu.so
pygcransac/__init__.py
pygcransac.libs/libgomp-a34b3233.so.1.0.0
pygcransac.libs/libopencv_core-61e74dbf.so.3.4.5
pygcransac.libs/libopencv_flann-80c081ea.so.3.4.5
pygcransac.libs/libopencv_calib3d-b2e6635f.so.3.4.5
pygcransac.libs/libopencv_features2d-0eb98270.so.3.4.5
pygcransac.libs/libopencv_imgproc-458179af.so.3.4.5
