Metadata-Version: 2.1
Name: pygcransac
Version: 0.1.1
Summary: Graph-Cut RANSAC
Author: Daniel Barath, Dmytro Mishkin
Author-email: barath.daniel@sztaki.mta.hu
License-File: LICENSE
Requires-Dist: numpy
